pro_fun/__init__.py
pro_fun/main.py
pro_fun/miracle.py
pro_fun-1.0.3.dist-info/METADATA
pro_fun-1.0.3.dist-info/WHEEL
pro_fun-1.0.3.dist-info/licenses/LICENSE
pro_fun-1.0.3.dist-info/RECORD
