Metadata-Version: 2.1
Name: pro_fun
Version: 1.0.3
Summary: Resolve simple client
Project-URL: Homepage, https://github.com/pypa/resolve
Project-URL: Issues, https://github.com/pypa/resolve/issues
Author-email: John Dallas <jdallas@gmail.com>
License-Expression: MIT
License-File: LICENSE
Classifier: Operating System :: OS Independent
Classifier: Programming Language :: Python :: 3
Requires-Python: >=3.9
Requires-Dist: cryptography>45.0.0
